domika_ha_framework/__init__.py
domika_ha_framework/alembic.ini
domika_ha_framework/config.py
domika_ha_framework/errors.py
domika_ha_framework/logger.py
domika_ha_framework/models.py
domika_ha_framework/push_server_errors.py
domika_ha_framework/statuses.py
domika_ha_framework/utils.py
domika_ha_framework/dashboard/__init__.py
domika_ha_framework/dashboard/models.py
domika_ha_framework/dashboard/service.py
domika_ha_framework/database/__init__.py
domika_ha_framework/database/core.py
domika_ha_framework/database/manage.py
domika_ha_framework/device/__init__.py
domika_ha_framework/device/flow.py
domika_ha_framework/device/models.py
domika_ha_framework/device/service.py
domika_ha_framework/migrations/README
domika_ha_framework/migrations/__init__.py
domika_ha_framework/migrations/env.py
domika_ha_framework/migrations/script.py.mako
domika_ha_framework/migrations/versions/3e2eb2f9d056_change_pushdata_primary_key.py
domika_ha_framework/migrations/versions/4c09d7fe055a_initial_revision.py
domika_ha_framework/migrations/versions/8e9c73bb3020_add_original_timestamp_and_domain_to_.py
domika_ha_framework/migrations/versions/9291d34e8062_added_temporary_event_table.py
domika_ha_framework/migrations/versions/939806f0fa92_add_push_token_hash_to_devices.py
domika_ha_framework/migrations/versions/b74951a1e96b_pushdata_id_to_event_id.py
domika_ha_framework/migrations/versions/b81792ef39a1_add_user_id_to_device.py
domika_ha_framework/migrations/versions/d9d8c5c24b47_upgrade_dashboards.py
domika_ha_framework/push_data/__init__.py
domika_ha_framework/push_data/flow.py
domika_ha_framework/push_data/models.py
domika_ha_framework/push_data/service.py
domika_ha_framework/subscription/__init__.py
domika_ha_framework/subscription/flow.py
domika_ha_framework/subscription/models.py
domika_ha_framework/subscription/service.py
domika_ha_framework-0.0.3.dist-info/LICENSE
domika_ha_framework-0.0.3.dist-info/METADATA
domika_ha_framework-0.0.3.dist-info/WHEEL
domika_ha_framework-0.0.3.dist-info/top_level.txt
domika_ha_framework-0.0.3.dist-info/RECORD
